{
  "project_info": {
    "project_number": "950038086264",
    "project_id": "task-demo-80524",
    "storage_bucket": "task-demo-80524.appspot.com"
  },
  "client": [
    {
      "client_info": {
        "mobilesdk_app_id": "1:950038086264:android:4ac2c08a5c9a27068e238d",
        "android_client_info": {
          "package_name": "com.example.taskdemo"
        }
      },
      "oauth_client": [
        {
          "client_id": "950038086264-em0cre99u7gvre3s451igcmuaimqn17j.apps.googleusercontent.com",
          "client_type": 3
        }
      ],
      "api_key": [
        {
          "current_key": "AIzaSyAnLApCWbjaOj4m1SMW4bCSoJScK73NoBE"
        }
      ],
      "services": {
        "appinvite_service": {
          "other_platform_oauth_client": [
            {
              "client_id": "950038086264-em0cre99u7gvre3s451igcmuaimqn17j.apps.googleusercontent.com",
              "client_type": 3
            }
          ]
        }
      }
    }
  ],
  "configuration_version": "1"
}